tinyDA/__init__.py
tinyDA/chain.py
tinyDA/diagnostics.py
tinyDA/distributions.py
tinyDA/link.py
tinyDA/posterior.py
tinyDA/proposal.py
tinyDA/ray.py
tinyDA/sampler.py
tinyDA/umbridge.py
tinyDA/utils.py
tinyda-0.9.21.dist-info/LICENSE
tinyda-0.9.21.dist-info/METADATA
tinyda-0.9.21.dist-info/WHEEL
tinyda-0.9.21.dist-info/RECORD
