Metadata-Version: 2.3
Name: tinyda
Version: 0.9.21
Summary: Delayed Acceptance MCMC Sampler
License: MIT
Author: Mikkel Bue Lykkegaard
Author-email: mikkelbue@gmail.com
Requires-Python: >=3.10,<4.0.0
Classifier: License :: OSI Approved :: MIT License
Classifier: Operating System :: OS Independent
Classifier: Programming Language :: Python :: 3
Classifier: Programming Language :: Python :: 3.10
Classifier: Programming Language :: Python :: 3.11
Classifier: Programming Language :: Python :: 3.12
Classifier: Programming Language :: Python :: 3.13
Requires-Dist: arviz (>=0.18.0,<0.19.0)
Requires-Dist: matplotlib (>=3.8.0,<4.0.0)
Requires-Dist: numpy (>=1.26.0,<2.0.0)
Requires-Dist: scipy (>=1.12.0,<2.0.0)
Requires-Dist: tqdm (>=4.66.0,<5.0.0)
Project-URL: Bug Tracker, https://github.com/mikkelbue/tinyDA/issues
Project-URL: Documentation, https://tinyda.readthedocs.io
Project-URL: Repository, https://github.com/mikkelbue/tinyda
